tinman_openclaw_eval/__init__.py
tinman_openclaw_eval/cli.py
tinman_openclaw_eval/harness.py
tinman_openclaw_eval/report.py
tinman_openclaw_eval/synthetic_gateway.py
tinman_openclaw_eval/tinman_integration.py
tinman_openclaw_eval/adapters/__init__.py
tinman_openclaw_eval/adapters/openclaw.py
tinman_openclaw_eval/attacks/__init__.py
tinman_openclaw_eval/attacks/base.py
tinman_openclaw_eval/attacks/context_bleed.py
tinman_openclaw_eval/attacks/evasion_bypass.py
tinman_openclaw_eval/attacks/financial.py
tinman_openclaw_eval/attacks/indirect_injection.py
tinman_openclaw_eval/attacks/mcp_attacks.py
tinman_openclaw_eval/attacks/memory_poisoning.py
tinman_openclaw_eval/attacks/platform_specific.py
tinman_openclaw_eval/attacks/privilege_escalation.py
tinman_openclaw_eval/attacks/prompt_injection.py
tinman_openclaw_eval/attacks/supply_chain.py
tinman_openclaw_eval/attacks/tool_exfil.py
tinman_openclaw_eval/attacks/unauthorized_action.py
tinman_openclaw_eval-0.3.1.dist-info/METADATA
tinman_openclaw_eval-0.3.1.dist-info/WHEEL
tinman_openclaw_eval-0.3.1.dist-info/entry_points.txt
tinman_openclaw_eval-0.3.1.dist-info/licenses/LICENSE
tinman_openclaw_eval-0.3.1.dist-info/RECORD
