Metadata-Version: 2.4
Name: tinman-openclaw-eval
Version: 0.3.1
Summary: Security evaluation harness for OpenClaw agents - powered by Tinman
Project-URL: Homepage, https://github.com/oliveskin/tinman-openclaw-eval
Project-URL: Repository, https://github.com/oliveskin/tinman-openclaw-eval
Project-URL: Issues, https://github.com/oliveskin/tinman-openclaw-eval/issues
Author: oliveskin
License-Expression: Apache-2.0
License-File: LICENSE
Keywords: ai-safety,evaluation,openclaw,red-team,security,tinman
Classifier: Development Status :: 4 - Beta
Classifier: Intended Audience :: Developers
Classifier: License :: OSI Approved :: Apache Software License
Classifier: Programming Language :: Python :: 3
Classifier: Programming Language :: Python :: 3.10
Classifier: Programming Language :: Python :: 3.11
Classifier: Programming Language :: Python :: 3.12
Classifier: Topic :: Scientific/Engineering :: Artificial Intelligence
Classifier: Topic :: Security
Requires-Python: >=3.10
Requires-Dist: agenttinman>=0.1.60
Requires-Dist: click>=8.0
Requires-Dist: httpx>=0.27.0
Requires-Dist: pyyaml>=6.0
Requires-Dist: rich>=13.0
Requires-Dist: websockets>=12.0
Provides-Extra: dev
Requires-Dist: pytest-asyncio>=0.23; extra == 'dev'
Requires-Dist: pytest-cov>=4.0; extra == 'dev'
Requires-Dist: pytest>=8.0; extra == 'dev'
Requires-Dist: ruff>=0.1.0; extra == 'dev'
